liquichange/__init__.py
liquichange/changelog.py
liquichange/element.py
liquichange/precondition.py
liquichange-0.2.2.dist-info/LICENSE
liquichange-0.2.2.dist-info/METADATA
liquichange-0.2.2.dist-info/WHEEL
liquichange-0.2.2.dist-info/RECORD
