Metadata-Version: 2.3
Name: liquichange
Version: 0.2.2
Summary: Build and modify Liquibase changelogs in Python.
License: Apache-2.0
Author: Nelson Moore
Author-email: nelson.moore@essential-soft.com
Requires-Python: >=3.9,<4.0
Classifier: License :: OSI Approved :: Apache Software License
Classifier: Programming Language :: Python :: 3
Classifier: Programming Language :: Python :: 3.9
Classifier: Programming Language :: Python :: 3.10
Classifier: Programming Language :: Python :: 3.11
Classifier: Programming Language :: Python :: 3.12
Classifier: Programming Language :: Python :: 3.13
Provides-Extra: dev
Requires-Dist: myst-nb (>=0.17.1) ; extra == "dev"
Requires-Dist: pytest (>=8.3.5)
Requires-Dist: pytest-cov (>=4.0.0) ; extra == "dev"
Requires-Dist: sphinx-autoapi (>=2.1.0) ; extra == "dev"
Requires-Dist: sphinx-rtd-theme (>=1.2.0) ; extra == "dev"
